tkitAutoMask/__init__.py
tkitAutoMask/attention_mask.py
tkitAutoMask/mask.py
tkitAutoMask/spanmask.py
tkitAutoMask-0.0.0.316483919.dist-info/LICENSE
tkitAutoMask-0.0.0.316483919.dist-info/METADATA
tkitAutoMask-0.0.0.316483919.dist-info/WHEEL
tkitAutoMask-0.0.0.316483919.dist-info/top_level.txt
tkitAutoMask-0.0.0.316483919.dist-info/RECORD
