Metadata-Version: 2.1
Name: tkitAutoMask
Version: 0.0.0.316483919
Summary: Terry toolkit tkitAutoMask,
Home-page: https://docs.terrychan.org/tkit-automask/
Author: Terry Chan
Author-email: napoler2008@gmail.com
License: UNKNOWN
Platform: UNKNOWN
